casting/cast/query/__init__.py
casting/cast/query/knowledge_base.py
casting/cast/query/rag/README.md
casting/cast/query/rag/__init__.py
casting/cast/query/rag/__main__.py
casting/cast/query/rag/api.py
casting/cast/query/rag/chroma_store.py
casting/cast/query/rag/chunking.py
casting/cast/query/rag/embeddings.py
casting/cast/query/rag/indexer.py
cast_query-0.1.0.dist-info/WHEEL
cast_query-0.1.0.dist-info/METADATA
cast_query-0.1.0.dist-info/RECORD
