Metadata-Version: 2.3
Name: cast-query
Version: 0.1.0
Summary: Cast knowledge base helpers
Requires-Dist: litellm>=1.44.4
Requires-Dist: chromadb>=0.5.0
Requires-Dist: pytest>=8.3.0 ; extra == 'dev'
Requires-Python: >=3.13
Provides-Extra: dev
